primenumbersfunction/__init__.py
primenumbersfunction-1.0.dist-info/LICENSE.txt
primenumbersfunction-1.0.dist-info/METADATA
primenumbersfunction-1.0.dist-info/WHEEL
primenumbersfunction-1.0.dist-info/top_level.txt
primenumbersfunction-1.0.dist-info/RECORD
