Metadata-Version: 2.1
Name: primenumbersfunction
Version: 1.0
Summary: A tool to determine prime numbers.
Home-page: UNKNOWN
Author: Ana García
Author-email: anagr.2812@gmail.com
License: GNU GPLv3
Keywords: prime numbers function
Platform: UNKNOWN
Classifier: Development Status :: 4 - Beta
Classifier: Intended Audience :: Developers
Classifier: Topic :: Utilities
Classifier: License :: OSI Approved :: GNU General Public License v3 (GPLv3)
Classifier: Programming Language :: Python :: 3
Classifier: Operating System :: OS Independent
